MANIFEST.in
setup.py
src/cameria/__init__.py
src/cameria/cameria.wsgi
src/cameria/main.py
src/cameria.egg-info/PKG-INFO
src/cameria.egg-info/SOURCES.txt
src/cameria.egg-info/dependency_links.txt
src/cameria.egg-info/not-zip-safe
src/cameria.egg-info/requires.txt
src/cameria.egg-info/top_level.txt
src/cameria/models/__init__.py
src/cameria/models/account.py
src/cameria/models/base.py
src/cameria/models/camera.py
src/cameria/models/device.py
src/cameria/models/set.py
src/cameria/models/spec.py
src/cameria/static/css/layout.css
src/cameria/static/images/favicon.ico
src/cameria/static/images/pattern.png
src/cameria/static/js/main.js
src/cameria/templates/about.html.tpl
src/cameria/templates/error.html.tpl
src/cameria/templates/index.html.tpl
src/cameria/templates/signin.html.tpl
src/cameria/templates/account/edit.html.tpl
src/cameria/templates/account/list.html.tpl
src/cameria/templates/account/new.html.tpl
src/cameria/templates/account/show.html.tpl
src/cameria/templates/camera/edit.html.tpl
src/cameria/templates/camera/list.html.tpl
src/cameria/templates/camera/new.html.tpl
src/cameria/templates/camera/settings.html.tpl
src/cameria/templates/camera/show.html.tpl
src/cameria/templates/device/edit.html.tpl
src/cameria/templates/device/list.html.tpl
src/cameria/templates/device/new.html.tpl
src/cameria/templates/device/show.html.tpl
src/cameria/templates/partials/content_type.html.tpl
src/cameria/templates/partials/doctype.html.tpl
src/cameria/templates/partials/end_doctype.html.tpl
src/cameria/templates/partials/footer.html.tpl
src/cameria/templates/partials/includes.html.tpl
src/cameria/templates/partials/layout.html.tpl
src/cameria/templates/partials/layout_account.html.tpl
src/cameria/templates/partials/layout_account_l.html.tpl
src/cameria/templates/partials/layout_camera.html.tpl
src/cameria/templates/partials/layout_camera_f.html.tpl
src/cameria/templates/partials/layout_camera_l.html.tpl
src/cameria/templates/partials/layout_device.html.tpl
src/cameria/templates/partials/layout_device_l.html.tpl
src/cameria/templates/partials/layout_full.html.tpl
src/cameria/templates/partials/layout_set.html.tpl
src/cameria/templates/partials/layout_set_f.html.tpl
